capnp-stubs/LICENSE
capnp-stubs/__init__.py
capnp-stubs/__init__.pyi
capnp-stubs/_internal.pyi
capnp-stubs/lib/__init__.pyi
capnp-stubs/lib/capnp.pyi
capnp-stubs/py.typed
capnp-stubs/version.pyi
mas/__init__.py
mas/__init__.pyi
mas/schema/__init__.py
mas/schema/__init__.pyi
mas/schema/climate/__init__.py
mas/schema/climate/__init__.pyi
mas/schema/climate/climate_capnp/__init__.py
mas/schema/climate/climate_capnp/__init__.pyi
mas/schema/cluster/__init__.py
mas/schema/cluster/__init__.pyi
mas/schema/cluster/cluster_admin_service_capnp/__init__.py
mas/schema/cluster/cluster_admin_service_capnp/__init__.pyi
mas/schema/common/__init__.py
mas/schema/common/__init__.pyi
mas/schema/common/common_capnp/__init__.py
mas/schema/common/common_capnp/__init__.pyi
mas/schema/common/date_capnp/__init__.py
mas/schema/common/date_capnp/__init__.pyi
mas/schema/config/__init__.py
mas/schema/config/__init__.pyi
mas/schema/config/config_capnp/__init__.py
mas/schema/config/config_capnp/__init__.pyi
mas/schema/crop/__init__.py
mas/schema/crop/__init__.pyi
mas/schema/crop/crop_capnp/__init__.py
mas/schema/crop/crop_capnp/__init__.pyi
mas/schema/dakis/__init__.py
mas/schema/dakis/__init__.pyi
mas/schema/dakis/modam/__init__.py
mas/schema/dakis/modam/__init__.pyi
mas/schema/dakis/modam/modam_capnp/__init__.py
mas/schema/dakis/modam/modam_capnp/__init__.pyi
mas/schema/data/__init__.py
mas/schema/data/__init__.pyi
mas/schema/data/field_exp_data_capnp/__init__.py
mas/schema/data/field_exp_data_capnp/__init__.pyi
mas/schema/fbp/__init__.py
mas/schema/fbp/__init__.pyi
mas/schema/fbp/fbp_capnp/__init__.py
mas/schema/fbp/fbp_capnp/__init__.pyi
mas/schema/geo/__init__.py
mas/schema/geo/__init__.pyi
mas/schema/geo/geo_capnp/__init__.py
mas/schema/geo/geo_capnp/__init__.pyi
mas/schema/grid/__init__.py
mas/schema/grid/__init__.pyi
mas/schema/grid/grid_capnp/__init__.py
mas/schema/grid/grid_capnp/__init__.pyi
mas/schema/jobs/__init__.py
mas/schema/jobs/__init__.pyi
mas/schema/jobs/jobs_capnp/__init__.py
zalfmas_capnp_schemas-0.1.48.dist-info/METADATA
zalfmas_capnp_schemas-0.1.48.dist-info/WHEEL
zalfmas_capnp_schemas-0.1.48.dist-info/licenses/LICENSE
zalfmas_capnp_schemas-0.1.48.dist-info/RECORD
