Metadata-Version: 2.4
Name: zalfmas-capnp-schemas
Version: 0.1.48
Summary: 
License-File: LICENSE
Author: Michael Berg-Mohnicke
Author-email: michael.berg@zalf.de
Requires-Python: >=3.10,<3.14
Classifier: Programming Language :: Python :: 3
Classifier: Programming Language :: Python :: 3.10
Classifier: Programming Language :: Python :: 3.11
Classifier: Programming Language :: Python :: 3.12
Classifier: Programming Language :: Python :: 3.13
Requires-Dist: pycapnp (>=2.2.1,<3.0.0)
